{
    "key": "group_6422fe1ec7065",
    "title": "BLOCK: Icon Blocks",
    "fields": [
        {
            "key": "field_6422ff1f2726e",
            "label": "Theme",
            "name": "theme",
            "aria-label": "",
            "type": "clone",
            "instructions": "",
            "required": 0,
            "conditional_logic": 0,
            "wrapper": {
                "width": "",
                "class": "",
                "id": ""
            },
            "clone": [
                "field_6408ad13ba71f"
            ],
            "display": "seamless",
            "layout": "block",
            "prefix_label": 0,
            "prefix_name": 0
        },
        {
            "key": "field_6422fe1f44c00",
            "label": "Icon Blocks",
            "name": "icon_blocks",
            "aria-label": "",
            "type": "repeater",
            "instructions": "",
            "required": 0,
            "conditional_logic": 0,
            "wrapper": {
                "width": "",
                "class": "",
                "id": ""
            },
            "layout": "block",
            "pagination": 0,
            "min": 0,
            "max": 0,
            "collapsed": "",
            "button_label": "Add Row",
            "rows_per_page": 20,
            "sub_fields": [
                {
                    "key": "field_6422fe3344c01",
                    "label": "Icon",
                    "name": "icon",
                    "aria-label": "",
                    "type": "font-awesome",
                    "instructions": "",
                    "required": 0,
                    "conditional_logic": 0,
                    "wrapper": {
                        "width": "30",
                        "class": "",
                        "id": ""
                    },
                    "icon_sets": [
                        "solid",
                        "regular",
                        "brands"
                    ],
                    "custom_icon_set": "",
                    "default_label": "",
                    "default_value": "",
                    "save_format": "element",
                    "allow_null": 0,
                    "show_preview": 1,
                    "enqueue_fa": 1,
                    "fa_live_preview": "",
                    "choices": [],
                    "parent_repeater": "field_6422fe1f44c00"
                },
                {
                    "key": "field_6422fedb1a724",
                    "label": "Title",
                    "name": "title",
                    "aria-label": "",
                    "type": "text",
                    "instructions": "",
                    "required": 0,
                    "conditional_logic": 0,
                    "wrapper": {
                        "width": "70",
                        "class": "",
                        "id": ""
                    },
                    "default_value": "",
                    "maxlength": "",
                    "placeholder": "",
                    "prepend": "",
                    "append": "",
                    "parent_repeater": "field_6422fe1f44c00"
                },
                {
                    "key": "field_6422fef51a725",
                    "label": "Description",
                    "name": "description",
                    "aria-label": "",
                    "type": "textarea",
                    "instructions": "",
                    "required": 0,
                    "conditional_logic": 0,
                    "wrapper": {
                        "width": "",
                        "class": "",
                        "id": ""
                    },
                    "default_value": "Limited to 135 characters.",
                    "maxlength": 135,
                    "rows": 3,
                    "placeholder": "",
                    "new_lines": "wpautop",
                    "parent_repeater": "field_6422fe1f44c00"
                }
            ]
        }
    ],
    "location": [
        [
            {
                "param": "block",
                "operator": "==",
                "value": "acf\/icon-blocks"
            }
        ]
    ],
    "menu_order": 0,
    "position": "normal",
    "style": "default",
    "label_placement": "top",
    "instruction_placement": "label",
    "hide_on_screen": "",
    "active": true,
    "description": "",
    "show_in_rest": 0,
    "modified": 1680018048
}